dataset_risk_decorator/__init__.py
dataset_risk_decorator/core.py
dataset_risk_decorator/test_dataset_risk_decorator.py
durinn_data_filter-0.1.7.dist-info/METADATA
durinn_data_filter-0.1.7.dist-info/WHEEL
durinn_data_filter-0.1.7.dist-info/licenses/LICENSE
durinn_data_filter-0.1.7.dist-info/RECORD
