Metadata-Version: 2.4
Name: durinn-data-filter
Version: 0.1.7
Summary: Risk-aware dataset decorator for Hugging Face datasets with automatic code detection and security risk labeling
License: Apache-2.0
License-File: LICENSE
Keywords: security,datasets,huggingface,mlops,code,safety
Author: Durinn
Author-email: victor@durinn.ai
Requires-Python: >=3.9,<3.13
Classifier: License :: OSI Approved :: Apache Software License
Classifier: Operating System :: OS Independent
Classifier: Programming Language :: Python :: 3
Classifier: Programming Language :: Python :: 3.9
Classifier: Programming Language :: Python :: 3.10
Classifier: Programming Language :: Python :: 3.11
Classifier: Programming Language :: Python :: 3.12
Classifier: Topic :: Scientific/Engineering :: Artificial Intelligence
Classifier: Topic :: Security
Requires-Dist: datasets (>=2.18.0)
Requires-Dist: huggingface-hub (>=0.23.0)
Requires-Dist: numpy (>=1.24.0)
Requires-Dist: pyarrow (>=15.0.0)
Requires-Dist: pytest (>=9.0.2)
Requires-Dist: torch (>=2.1.0)
Requires-Dist: tqdm (>=4.66.0)
Requires-Dist: transformers (>=4.40.0)
Requires-Dist: typing-extensions (>=4.9.0)
Project-URL: Homepage, https://durinn.ai
Project-URL: Repository, https://github.com/Durinn-Research/durinn-data-filter/tree/main
